remotepdb_client/__config__.py
remotepdb_client/__init__.py
remotepdb_client/remotepdb_client.py
remote_pdb_client-1.0.4.dist-info/LICENSE
remote_pdb_client-1.0.4.dist-info/METADATA
remote_pdb_client-1.0.4.dist-info/WHEEL
remote_pdb_client-1.0.4.dist-info/entry_points.txt
remote_pdb_client-1.0.4.dist-info/top_level.txt
remote_pdb_client-1.0.4.dist-info/RECORD
